label_centerlines/__init__.py
label_centerlines/_src.py
label_centerlines/cli.py
label_centerlines/exceptions.py
label_centerlines-2022.6.0.dist-info/LICENSE.rst
label_centerlines-2022.6.0.dist-info/METADATA
label_centerlines-2022.6.0.dist-info/WHEEL
label_centerlines-2022.6.0.dist-info/entry_points.txt
label_centerlines-2022.6.0.dist-info/top_level.txt
label_centerlines-2022.6.0.dist-info/RECORD
